caif/__init__.py
caif/data_handler.py
caif/error_handler.py
caif/model_core.py
caif/output_processor.py
caif/shortcuts.py
caif_framework-0.0.2.dist-info/licenses/LICENSE.txt
caif_framework-0.0.2.dist-info/METADATA
caif_framework-0.0.2.dist-info/WHEEL
caif_framework-0.0.2.dist-info/top_level.txt
caif_framework-0.0.2.dist-info/RECORD
