Metadata-Version: 2.4
Name: caif-framework
Version: 0.0.2
Summary: CAIF (Code AI Fast): A simple, fast framework for building any AI model.
Author-email: Rudra <rudra@caif.ai>
License: SEE LICENSE IN LICENSE.txt
Keywords: AI,machine learning,data,chatbot,nlp,fast-development
Classifier: Programming Language :: Python :: 3
Classifier: Operating System :: OS Independent
Classifier: Topic :: Scientific/Engineering :: Artificial Intelligence
Classifier: Development Status :: 3 - Alpha
Requires-Python: >=3.8
License-File: LICENSE.txt
Requires-Dist: numpy
Requires-Dist: pandas
Requires-Dist: scikit-learn
Requires-Dist: Pillow
Requires-Dist: PyYAML
Requires-Dist: openpyxl
Requires-Dist: markdown-it-py
Requires-Dist: requests
Dynamic: license-file
